setup.py
dnd_probability/Binomialdistribution.py
dnd_probability/Gaussiandistribution.py
dnd_probability/Generaldistribution.py
dnd_probability/__init__.py
dnd_probability.egg-info/PKG-INFO
dnd_probability.egg-info/SOURCES.txt
dnd_probability.egg-info/dependency_links.txt
dnd_probability.egg-info/not-zip-safe
dnd_probability.egg-info/top_level.txt