Metadata-Version: 1.0
Name: dnd-probability
Version: 1.2
Summary: Gaussian and Binomial distributions
Home-page: UNKNOWN
Author: Jeremiah Kamama
Author-email: UNKNOWN
License: UNKNOWN
Platform: UNKNOWN
